ddd_physical_units-0.0.0.dist-info/licenses/LICENSE
physical_units/__init__.py
physical_units/base_physical_unit.py
physical_units/meter.py
physical_units/meter_second.py
physical_units/second.py
ddd_physical_units-0.0.0.dist-info/METADATA
ddd_physical_units-0.0.0.dist-info/WHEEL
ddd_physical_units-0.0.0.dist-info/top_level.txt
ddd_physical_units-0.0.0.dist-info/RECORD
