Metadata-Version: 2.4
Name: ddd-physical-units
Version: 0.0.0
Summary: Support for units of measurement in domain-oriented design in Python.
Author-email: Pavel Shmakov <shmakovpn@yandex.ru>
License: MIT License
Project-URL: Homepage, https://github.com/shmakovpn/ddd-physical-units
Classifier: License :: OSI Approved :: MIT License
Classifier: Programming Language :: Python
Classifier: Programming Language :: Python :: 3
Requires-Python: >=3.9
License-File: LICENSE
Provides-Extra: dev
Requires-Dist: tomli; python_version < "3.11" and extra == "dev"
Requires-Dist: pip-tools; extra == "dev"
Requires-Dist: pytest; extra == "dev"
Requires-Dist: coverage; extra == "dev"
Requires-Dist: build; extra == "dev"
Dynamic: license-file
